allencell_ml_segmenter/__init__.py
allencell_ml_segmenter/_style.py
allencell_ml_segmenter/napari.yaml
allencell_ml_segmenter/_tests/__init__.py
allencell_ml_segmenter/_tests/test_style.py
allencell_ml_segmenter/_tests/config/test_user_settings.py
allencell_ml_segmenter/_tests/core/__init__.py
allencell_ml_segmenter/_tests/core/test_channel_extraction.py
allencell_ml_segmenter/_tests/core/test_dialog_box.py
allencell_ml_segmenter/_tests/core/test_directories.py
allencell_ml_segmenter/_tests/core/test_file_input_model.py
allencell_ml_segmenter/_tests/core/test_progress_tracker.py
allencell_ml_segmenter/_tests/core/test_publisher.py
allencell_ml_segmenter/_tests/curation/__init__.py
allencell_ml_segmenter/_tests/curation/test_curation_input_view.py
allencell_ml_segmenter/_tests/curation/test_curation_main.py
allencell_ml_segmenter/_tests/curation/test_curation_model.py
allencell_ml_segmenter/_tests/curation/test_curation_service.py
allencell_ml_segmenter/_tests/curation/test_curation_widget.py
allencell_ml_segmenter/_tests/curation/curation_tests/file1.ome.tiff
allencell_ml_segmenter/_tests/curation/curation_tests/file_test.ome.tiff
allencell_ml_segmenter/_tests/fakes/__init__.py
allencell_ml_segmenter/_tests/fakes/fake_channel_extraction.py
allencell_ml_segmenter/_tests/fakes/fake_experiments_model.py
allencell_ml_segmenter/_tests/fakes/fake_qsettings.py
allencell_ml_segmenter/_tests/fakes/fake_subscriber.py
allencell_ml_segmenter/_tests/fakes/fake_user_settings.py
allencell_ml_segmenter/_tests/fakes/fake_viewer.py
allencell_ml_segmenter/_tests/main/__init__.py
allencell_ml_segmenter/_tests/main/test_experiments_model.py
allencell_ml_segmenter/_tests/main/test_main_model.py
allencell_ml_segmenter/_tests/main/test_main_service.py
allencell_ml_segmenter/_tests/main/test_main_widget.py
allencell_ml_segmenter/_tests/main/test_viewer.py
allencell_ml_segmenter/_tests/main/experiments_home/0_exp/0.ckpt
allencell_segmenter_ml-1.0.0.dist-info/licenses/LICENSE
allencell_segmenter_ml-1.0.0.dist-info/METADATA
allencell_segmenter_ml-1.0.0.dist-info/WHEEL
allencell_segmenter_ml-1.0.0.dist-info/entry_points.txt
allencell_segmenter_ml-1.0.0.dist-info/top_level.txt
allencell_segmenter_ml-1.0.0.dist-info/RECORD
