Metadata-Version: 2.4
Name: allencell-segmenter-ml
Version: 1.0.0
Summary: A plugin to leverage ML segmentation in napari
License: Allen Institute Software License – This software license is the 2-clause BSD license plus clause a third clause that
Project-URL: Homepage, https://github.com/AllenCell/allencell-ml-segmenter
Project-URL: Bug Tracker, https://github.com/AllenCell/allencell-ml-segmenter/issues
Project-URL: Documentation, https://github.com/AllenCell/allencell-ml-segmenter#README.md
Project-URL: User Support, https://github.com/AllenCell/allencell-ml-segmenter/issues
Classifier: Development Status :: 2 - Pre-Alpha
Classifier: Framework :: napari
Classifier: Intended Audience :: Science/Research
Classifier: License :: Other/Proprietary License
Classifier: License :: Free for non-commercial use
Classifier: Operating System :: OS Independent
Classifier: Programming Language :: Python
Classifier: Programming Language :: Python :: 3
Classifier: Programming Language :: Python :: 3 :: Only
Classifier: Programming Language :: Python :: 3.9
Classifier: Programming Language :: Python :: 3.10
Classifier: Topic :: Scientific/Engineering :: Image Processing
Requires-Python: <3.11,>=3.9
License-File: LICENSE
Requires-Dist: npe2>=0.6.2
Requires-Dist: numpy
Requires-Dist: hydra-core==1.3.2
Requires-Dist: bioio==1.1.0
Requires-Dist: bioio-base==1.0.4
Requires-Dist: tifffile<2025.2.18,>=2023.4.12
Requires-Dist: watchdog
Requires-Dist: cyto-dl>=0.4.5
Requires-Dist: scikit-image!=0.23.0
Provides-Extra: napari
Requires-Dist: napari>=0.4.18; extra == "napari"
Requires-Dist: pyqt5; extra == "napari"
Provides-Extra: test-lint
Requires-Dist: pytest<8.0.0; extra == "test-lint"
Requires-Dist: pytest-cov; extra == "test-lint"
Requires-Dist: pytest-qt; extra == "test-lint"
Requires-Dist: qtpy; extra == "test-lint"
Requires-Dist: pyqt5; extra == "test-lint"
Requires-Dist: black>=24.2.0; extra == "test-lint"
Requires-Dist: pytest-xvfb; sys_platform == "linux" and extra == "test-lint"
Requires-Dist: responses; extra == "test-lint"
Requires-Dist: mypy; extra == "test-lint"
Requires-Dist: toml; extra == "test-lint"
Requires-Dist: bumpver; extra == "test-lint"
Requires-Dist: napari>=0.4.18; extra == "test-lint"
Requires-Dist: magicgui; extra == "test-lint"
Provides-Extra: dev
Requires-Dist: black>=24.2.0; extra == "dev"
Requires-Dist: coverage>=7.2.2; extra == "dev"
Requires-Dist: flake8>=6.0.0; extra == "dev"
Requires-Dist: pytest<8.0.0,>=7.2.2; extra == "dev"
Requires-Dist: pytest-qt>=3.3.0; extra == "dev"
Requires-Dist: pytest-cov>=2.6.1; extra == "dev"
Requires-Dist: pyqt5>=5.15.9; extra == "dev"
Requires-Dist: bumpver>=2023.1129; extra == "dev"
Requires-Dist: build>=1.0.3; extra == "dev"
Requires-Dist: twine>=5.0.0; extra == "dev"
Requires-Dist: responses; extra == "dev"
Requires-Dist: mypy; extra == "dev"
Provides-Extra: sphinx-docs
Requires-Dist: linkify-it-py; extra == "sphinx-docs"
Requires-Dist: sphinx; extra == "sphinx-docs"
Requires-Dist: furo; extra == "sphinx-docs"
Requires-Dist: sphinxext-opengraph; extra == "sphinx-docs"
Requires-Dist: sphinx_inline_tabs; extra == "sphinx-docs"
Requires-Dist: sphinx_copybutton; extra == "sphinx-docs"
Requires-Dist: myst_parser; extra == "sphinx-docs"
Requires-Dist: sphinx_togglebutton; extra == "sphinx-docs"
Requires-Dist: sphinx_design; extra == "sphinx-docs"
Dynamic: license-file
